src/__init__.py
clivo_lm-0.1.0.dist-info/METADATA
clivo_lm-0.1.0.dist-info/WHEEL
clivo_lm-0.1.0.dist-info/top_level.txt
clivo_lm-0.1.0.dist-info/RECORD
