Metadata-Version: 2.1
Name: clivo-lm
Version: 0.1.0
Summary: Clivo FP Framework
Home-page: UNKNOWN
License: MIT
Platform: UNKNOWN
Classifier: Programming Language :: Python :: 3
Classifier: License :: OSI Approved :: MIT License
Classifier: Operating System :: OS Independent
Requires-Python: >=3.8
